typer_cloup/__init__.py
typer_cloup/colors.py
typer_cloup/completion.py
typer_cloup/core.py
typer_cloup/main.py
typer_cloup/models.py
typer_cloup/param_types.py
typer_cloup/params.py
typer_cloup/py.typed
typer_cloup/testing.py
typer_cloup/utils.py
typer_cloup-0.11.0.dist-info/LICENSE
typer_cloup-0.11.0.dist-info/WHEEL
typer_cloup-0.11.0.dist-info/METADATA
typer_cloup-0.11.0.dist-info/RECORD
